gscrib/__init__.py
gscrib/codes/__init__.py
gscrib/codes/gcode_entry.py
gscrib/codes/gcode_mappings.py
gscrib/codes/gcode_table.py
gscrib/config.py
gscrib/enums/__init__.py
gscrib/enums/base_enum.py
gscrib/enums/modes/__init__.py
gscrib/enums/modes/direct_write.py
gscrib/enums/types/__init__.py
gscrib/enums/types/axis.py
gscrib/enums/types/bed_temperature.py
gscrib/enums/types/chamber_temperature.py
gscrib/enums/types/coolant_mode.py
gscrib/enums/types/direction.py
gscrib/enums/types/distance_mode.py
gscrib/enums/types/extrusion_mode.py
gscrib/enums/types/fan_mode.py
gscrib/enums/types/feed_mode.py
gscrib/enums/types/halt_mode.py
gscrib/enums/types/hotend_temperature.py
gscrib/enums/types/plane.py
gscrib/enums/types/positioning_mode.py
gscrib/enums/types/power_mode.py
gscrib/enums/types/probing_mode.py
gscrib/enums/types/query_mode.py
gscrib/enums/types/spin_mode.py
gscrib/enums/types/tool_swap_mode.py
gscrib/enums/units/__init__.py
gscrib/enums/units/length_units.py
gscrib/enums/units/temperature_units.py
gscrib/enums/units/time_units.py
gscrib/excepts/__init__.py
gscrib/excepts/device_errors.py
gscrib/excepts/gcode_errors.py
gscrib/excepts/gscrib_errors.py
gscrib/formatters/__init__.py
gscrib/formatters/base_formatter.py
gscrib/formatters/default_formatter.py
gscrib/gcode_builder.py
gscrib/gcode_core.py
gscrib/gcode_state.py
gscrib/geometry/__init__.py
gscrib/geometry/bounds.py
gscrib/geometry/point.py
gscrib/geometry/tracer.py
gscrib/geometry/transform.py
gscrib/geometry/transformer.py
gscrib/hooks/__init__.py
gscrib/hooks/extrusion_hook.py
gscrib/params.py
gscrib/printrun/__init__.py
gscrib/printrun/device.py
gscrib/printrun/eventhandler.py
gscrib/printrun/gcoder.py
gscrib/printrun/printcore.py
gscrib/types/__init__.py
gscrib/writers/__init__.py
gscrib/writers/base_writer.py
gscrib/writers/console_writer.py
gscrib/writers/file_writer.py
gscrib/writers/log_writer.py
gscrib/writers/printrun_writer.py
gscrib/writers/serial_writer.py
gscrib/writers/socket_writer.py
gscrib-1.1.0.dist-info/LICENSE
gscrib-1.1.0.dist-info/METADATA
gscrib-1.1.0.dist-info/WHEEL
gscrib-1.1.0.dist-info/RECORD
